[
  { "date": "2026-02-28", "page": "スキル玉合成", "route": "/SkillRoot", "content": "更新" },
  { "date": "2026-02-28", "page": "討伐デッキ統計", "route": "/RaidStatistics", "content": "更新" },
  { "date": "2026-02-24", "page": "SGの使い道【無償】", "route": "/SgFree", "content": "開設" },
  { "date": "2026-02-24", "page": "スキル玉合成", "route": "/SkillRoot", "content": "更新" },
  { "date": "2026-02-07", "page": "討伐デッキ統計", "route": "/RaidStatistics", "content": "開設" },
  { "date": "2026-01-31", "page": "武将-神将", "route": "/ReviewShinsho", "content": "更新" },
  { "date": "2026-01-30", "page": "大将-合戦", "route": "/ReviewKassen", "content": "更新" },
  { "date": "2026-01-30", "page": "大将-レイド", "route": "/ReviewRaid", "content": "更新" },
  { "date": "2026-01-30", "page": "武将-天将", "route": "/ReviewTensho", "content": "更新" },
  { "date": "2026-01-30", "page": "武将-覇王", "route": "/ReviewHaou", "content": "更新" },
  { "date": "2026-01-06", "page": "シリアルコード", "route": "/SerialCode", "content": "開設" },
  { "date": "2026-01-06", "page": "データ-スキル", "route": "/DataSkill", "content": "更新" },
  { "date": "2026-01-06", "page": "大将-合戦", "route": "/ReviewKassen", "content": "更新" },
  { "date": "2026-01-06", "page": "大将-レイド", "route": "/ReviewRaid", "content": "更新" },
  { "date": "2025-12-20", "page": "レイド統計", "route": "/RaidStatistics", "content": "開設" },
  { "date": "2025-12-17", "page": "大将-合戦", "route": "/ReviewKassen", "content": "更新" },
  { "date": "2025-12-17", "page": "大将-レイド", "route": "/ReviewRaid", "content": "更新" },
  { "date": "2025-12-06", "page": "データ-スキル", "route": "/DataSkill", "content": "更新" },
  { "date": "2025-12-06", "page": "データ-奥義", "route": "/DataOugi", "content": "更新" },
  { "date": "2025-12-04", "page": "大将-レイド", "route": "/ReviewRaid", "content": "更新" },
  { "date": "2025-12-04", "page": "大将-合戦", "route": "/ReviewKassen", "content": "更新" },
  { "date": "2025-12-04", "page": "データ-スキル", "route": "/DataSkill", "content": "更新" },
  { "date": "2025-11-27", "page": "スキル玉合成", "route": "/SkillRoot", "content": "更新" },
  { "date": "2025-11-23", "page": "デッキ-レイド", "route": "/DeckRaid", "content": "開設" },
  { "date": "2025-11-22", "page": "スキル玉合成", "route": "/SkillRoot", "content": "更新" },
  { "date": "2025-11-21", "page": "スキル玉合成", "route": "/SkillRoot", "content": "更新" },
  { "date": "2025-11-20", "page": "スキル玉合成", "route": "/SkillRoot", "content": "更新" },
  { "date": "2025-11-19", "page": "スキル玉合成", "route": "/SkillRoot", "content": "開設" },
  { "date": "2025-11-17", "page": "ALL", "route": "/", "content": "開設" }
]